pyp2qmd/Config.py
pyp2qmd/DocConverter.py
pyp2qmd/ManPage.py
pyp2qmd/__init__.py
pyp2qmd/demofunctions.py
pyp2qmd/bin/pyp2qmd.py
pyp2qmd/templates/_quarto.yml
pyp2qmd/templates/index.qmd
pyp2qmd/templates/pyp.scss
pyp2qmd-0.1.2.dist-info/licenses/LICENSE.txt
pyp2qmd-0.1.2.dist-info/METADATA
pyp2qmd-0.1.2.dist-info/WHEEL
pyp2qmd-0.1.2.dist-info/entry_points.txt
pyp2qmd-0.1.2.dist-info/top_level.txt
pyp2qmd-0.1.2.dist-info/RECORD
