Metadata-Version: 2.4
Name: pyp2qmd
Version: 0.1.2
Summary: Parses docstrings of all exported classes and methods of a python package and turns them into quarto markdown (qmd) files. Alongside, a basic structure for a quarto website is created, intended to easily document your python package with quarto.
Home-page: https://github.com/retostauffer/pyp2qmd
Author: Reto Stauffer
Author-email: reto.stauffer@uibk.ac.at
License: GNU General Public License v2.0 or later
Project-URL: GitHub Issues, https://github.com/retostauffer/pyp2qmd/issues
Classifier: Development Status :: 3 - Alpha
Classifier: Programming Language :: Python :: 3
Classifier: Operating System :: OS Independent
Requires-Python: >=3.8
License-File: LICENSE.txt
Requires-Dist: docstring_parser
Requires-Dist: pyyaml
Dynamic: author
Dynamic: author-email
Dynamic: classifier
Dynamic: description
Dynamic: description-content-type
Dynamic: home-page
Dynamic: license
Dynamic: license-file
Dynamic: project-url
Dynamic: requires-dist
Dynamic: requires-python
Dynamic: summary
